main.py
mcp_read_pdf-0.1.1.dist-info/licenses/LICENSE
mcp_read_pdf-0.1.1.dist-info/METADATA
mcp_read_pdf-0.1.1.dist-info/WHEEL
mcp_read_pdf-0.1.1.dist-info/entry_points.txt
mcp_read_pdf-0.1.1.dist-info/top_level.txt
mcp_read_pdf-0.1.1.dist-info/RECORD
