Metadata-Version: 2.4
Name: mcp-read-pdf
Version: 0.1.1
Summary: PDF reader extension for MCP that can work with large PDFs and password protected.
Author: Michael Neale
License: MIT
Project-URL: Homepage, https://github.com/michaelneale/mcp-read-pdf/
Requires-Python: >=3.12
License-File: LICENSE
Requires-Dist: mcp[cli]>=1.3.0
Requires-Dist: pypdf2>=3.0.1
Dynamic: license-file
